[
    {
        "accuracy": 0.9512,
        "all_blocks_num": 54,
        "blocks_array": [
            18,
            18,
            18,
            0
        ],
        "i": -1,
        "num_blocks_active": 54,
        "num_blocks_removed": 0,
        "recalc_cache": false,
        "removed_blocks": [],
        "topk_dict": {
            "top1": 0.9512
        },
        "trained": false
    },
    {
        "accuracy": 0.9506,
        "block": 19,
        "i": 0,
        "num_blocks_active": 53,
        "num_blocks_removed": 1,
        "recalc_cache": true,
        "removed_blocks": [
            19
        ],
        "topk_dict": {
            "top1": 0.9506
        },
        "trained": false
    },
    {
        "accuracy": 0.9504,
        "accuracy_before_training": 0.9492,
        "block": 33,
        "epochs": 16,
        "i": 1,
        "num_blocks_active": 52,
        "num_blocks_removed": 2,
        "recalc_cache": true,
        "removed_blocks": [
            19,
            33
        ],
        "topk_dict": {
            "top1": 0.9504
        },
        "trained": {
            "accuracy": 0.9504,
            "accuracy_gain": 0.0011999999999999789,
            "checkpoint": "/scratch/vsv1g12/distillation/every_two_step-e50/to-ResNet-56/temp-4/alpha-0.5/baseline_1/0/iter_1_removed_2.pth.tar",
            "duration": 1941.6759986877441,
            "epochs": 16,
            "event": "trained",
            "i": 1,
            "iteration": 1,
            "removed_blocks": [
                19,
                33
            ],
            "topk_dict": {
                "top1": 0.9504
            },
            "total_epochs": 50
        }
    },
    {
        "accuracy": 0.9482,
        "block": 10,
        "i": 2,
        "num_blocks_active": 51,
        "num_blocks_removed": 3,
        "recalc_cache": true,
        "removed_blocks": [
            19,
            33,
            10
        ],
        "topk_dict": {
            "top1": 0.9482
        },
        "trained": false
    },
    {
        "accuracy": 0.95,
        "accuracy_before_training": 0.9466,
        "block": 21,
        "epochs": 36,
        "i": 3,
        "num_blocks_active": 50,
        "num_blocks_removed": 4,
        "recalc_cache": true,
        "removed_blocks": [
            19,
            33,
            10,
            21
        ],
        "topk_dict": {
            "top1": 0.95
        },
        "trained": {
            "accuracy": 0.95,
            "accuracy_gain": 0.0033999999999999586,
            "checkpoint": "/scratch/vsv1g12/distillation/every_two_step-e50/to-ResNet-56/temp-4/alpha-0.5/baseline_1/0/iter_3_removed_4.pth.tar",
            "duration": 1887.7122197151184,
            "epochs": 36,
            "event": "trained",
            "i": 3,
            "iteration": 3,
            "removed_blocks": [
                19,
                33,
                10,
                21
            ],
            "topk_dict": {
                "top1": 0.95
            },
            "total_epochs": 50
        }
    },
    {
        "accuracy": 0.9488,
        "block": 27,
        "i": 4,
        "num_blocks_active": 49,
        "num_blocks_removed": 5,
        "recalc_cache": true,
        "removed_blocks": [
            19,
            33,
            10,
            21,
            27
        ],
        "topk_dict": {
            "top1": 0.9488
        },
        "trained": false
    },
    {
        "accuracy": 0.9498,
        "accuracy_before_training": 0.947,
        "block": 31,
        "epochs": 38,
        "i": 5,
        "num_blocks_active": 48,
        "num_blocks_removed": 6,
        "recalc_cache": true,
        "removed_blocks": [
            19,
            33,
            10,
            21,
            27,
            31
        ],
        "topk_dict": {
            "top1": 0.9498
        },
        "trained": {
            "accuracy": 0.9498,
            "accuracy_gain": 0.0028000000000000247,
            "checkpoint": "/scratch/vsv1g12/distillation/every_two_step-e50/to-ResNet-56/temp-4/alpha-0.5/baseline_1/0/iter_5_removed_6.pth.tar",
            "duration": 1849.7801115512848,
            "epochs": 38,
            "event": "trained",
            "i": 5,
            "iteration": 5,
            "removed_blocks": [
                19,
                33,
                10,
                21,
                27,
                31
            ],
            "topk_dict": {
                "top1": 0.9498
            },
            "total_epochs": 50
        }
    },
    {
        "accuracy": 0.9496,
        "block": 37,
        "i": 6,
        "num_blocks_active": 47,
        "num_blocks_removed": 7,
        "recalc_cache": true,
        "removed_blocks": [
            19,
            33,
            10,
            21,
            27,
            31,
            37
        ],
        "topk_dict": {
            "top1": 0.9496
        },
        "trained": false
    },
    {
        "accuracy": 0.9494,
        "accuracy_before_training": 0.9494,
        "block": 34,
        "epochs": 0,
        "i": 7,
        "num_blocks_active": 46,
        "num_blocks_removed": 8,
        "recalc_cache": true,
        "removed_blocks": [
            19,
            33,
            10,
            21,
            27,
            31,
            37,
            34
        ],
        "topk_dict": {
            "top1": 0.9494
        },
        "trained": {
            "accuracy": 0.9494,
            "accuracy_gain": 0.0,
            "checkpoint": "/scratch/vsv1g12/distillation/every_two_step-e50/to-ResNet-56/temp-4/alpha-0.5/baseline_1/0/iter_7_removed_8.pth.tar",
            "duration": 1809.0069751739502,
            "epochs": 0,
            "event": "trained",
            "i": 7,
            "iteration": 7,
            "removed_blocks": [
                19,
                33,
                10,
                21,
                27,
                31,
                37,
                34
            ],
            "topk_dict": {
                "top1": 0.9494
            },
            "total_epochs": 50
        }
    },
    {
        "accuracy": 0.9468,
        "block": 20,
        "i": 8,
        "num_blocks_active": 45,
        "num_blocks_removed": 9,
        "recalc_cache": true,
        "removed_blocks": [
            19,
            33,
            10,
            21,
            27,
            31,
            37,
            34,
            20
        ],
        "topk_dict": {
            "top1": 0.9468
        },
        "trained": false
    },
    {
        "accuracy": 0.9516,
        "accuracy_before_training": 0.9438,
        "block": 29,
        "epochs": 22,
        "i": 9,
        "num_blocks_active": 44,
        "num_blocks_removed": 10,
        "recalc_cache": true,
        "removed_blocks": [
            19,
            33,
            10,
            21,
            27,
            31,
            37,
            34,
            20,
            29
        ],
        "topk_dict": {
            "top1": 0.9516
        },
        "trained": {
            "accuracy": 0.9516,
            "accuracy_gain": 0.007800000000000029,
            "checkpoint": "/scratch/vsv1g12/distillation/every_two_step-e50/to-ResNet-56/temp-4/alpha-0.5/baseline_1/0/iter_9_removed_10.pth.tar",
            "duration": 1772.8203930854797,
            "epochs": 22,
            "event": "trained",
            "i": 9,
            "iteration": 9,
            "removed_blocks": [
                19,
                33,
                10,
                21,
                27,
                31,
                37,
                34,
                20,
                29
            ],
            "topk_dict": {
                "top1": 0.9516
            },
            "total_epochs": 50
        }
    },
    {
        "accuracy": 0.9478,
        "block": 43,
        "i": 10,
        "num_blocks_active": 43,
        "num_blocks_removed": 11,
        "recalc_cache": true,
        "removed_blocks": [
            19,
            33,
            10,
            21,
            27,
            31,
            37,
            34,
            20,
            29,
            43
        ],
        "topk_dict": {
            "top1": 0.9478
        },
        "trained": false
    },
    {
        "accuracy": 0.95,
        "accuracy_before_training": 0.9462,
        "block": 11,
        "epochs": 50,
        "i": 11,
        "num_blocks_active": 42,
        "num_blocks_removed": 12,
        "recalc_cache": true,
        "removed_blocks": [
            19,
            33,
            10,
            21,
            27,
            31,
            37,
            34,
            20,
            29,
            43,
            11
        ],
        "topk_dict": {
            "top1": 0.95
        },
        "trained": {
            "accuracy": 0.95,
            "accuracy_gain": 0.0037999999999999146,
            "checkpoint": "/scratch/vsv1g12/distillation/every_two_step-e50/to-ResNet-56/temp-4/alpha-0.5/baseline_1/0/iter_11_removed_12.pth.tar",
            "duration": 1721.1373174190521,
            "epochs": 50,
            "event": "trained",
            "i": 11,
            "iteration": 11,
            "removed_blocks": [
                19,
                33,
                10,
                21,
                27,
                31,
                37,
                34,
                20,
                29,
                43,
                11
            ],
            "topk_dict": {
                "top1": 0.95
            },
            "total_epochs": 50
        }
    },
    {
        "accuracy": 0.9486,
        "block": 35,
        "i": 12,
        "num_blocks_active": 41,
        "num_blocks_removed": 13,
        "recalc_cache": true,
        "removed_blocks": [
            19,
            33,
            10,
            21,
            27,
            31,
            37,
            34,
            20,
            29,
            43,
            11,
            35
        ],
        "topk_dict": {
            "top1": 0.9486
        },
        "trained": false
    },
    {
        "accuracy": 0.9524,
        "accuracy_before_training": 0.9452,
        "block": 49,
        "epochs": 41,
        "i": 13,
        "num_blocks_active": 40,
        "num_blocks_removed": 14,
        "recalc_cache": true,
        "removed_blocks": [
            19,
            33,
            10,
            21,
            27,
            31,
            37,
            34,
            20,
            29,
            43,
            11,
            35,
            49
        ],
        "topk_dict": {
            "top1": 0.9524
        },
        "trained": {
            "accuracy": 0.9524,
            "accuracy_gain": 0.007199999999999984,
            "checkpoint": "/scratch/vsv1g12/distillation/every_two_step-e50/to-ResNet-56/temp-4/alpha-0.5/baseline_1/0/iter_13_removed_14.pth.tar",
            "duration": 1686.402426958084,
            "epochs": 41,
            "event": "trained",
            "i": 13,
            "iteration": 13,
            "removed_blocks": [
                19,
                33,
                10,
                21,
                27,
                31,
                37,
                34,
                20,
                29,
                43,
                11,
                35,
                49
            ],
            "topk_dict": {
                "top1": 0.9524
            },
            "total_epochs": 50
        }
    },
    {
        "accuracy": 0.9472,
        "block": 14,
        "i": 14,
        "num_blocks_active": 39,
        "num_blocks_removed": 15,
        "recalc_cache": true,
        "removed_blocks": [
            19,
            33,
            10,
            21,
            27,
            31,
            37,
            34,
            20,
            29,
            43,
            11,
            35,
            49,
            14
        ],
        "topk_dict": {
            "top1": 0.9472
        },
        "trained": false
    },
    {
        "accuracy": 0.9492,
        "accuracy_before_training": 0.9436,
        "block": 39,
        "epochs": 28,
        "i": 15,
        "num_blocks_active": 38,
        "num_blocks_removed": 16,
        "recalc_cache": true,
        "removed_blocks": [
            19,
            33,
            10,
            21,
            27,
            31,
            37,
            34,
            20,
            29,
            43,
            11,
            35,
            49,
            14,
            39
        ],
        "topk_dict": {
            "top1": 0.9492
        },
        "trained": {
            "accuracy": 0.9492,
            "accuracy_gain": 0.005600000000000049,
            "checkpoint": "/scratch/vsv1g12/distillation/every_two_step-e50/to-ResNet-56/temp-4/alpha-0.5/baseline_1/0/iter_15_removed_16.pth.tar",
            "duration": 1634.7645299434662,
            "epochs": 28,
            "event": "trained",
            "i": 15,
            "iteration": 15,
            "removed_blocks": [
                19,
                33,
                10,
                21,
                27,
                31,
                37,
                34,
                20,
                29,
                43,
                11,
                35,
                49,
                14,
                39
            ],
            "topk_dict": {
                "top1": 0.9492
            },
            "total_epochs": 50
        }
    },
    {
        "accuracy": 0.9468,
        "block": 9,
        "i": 16,
        "num_blocks_active": 37,
        "num_blocks_removed": 17,
        "recalc_cache": true,
        "removed_blocks": [
            19,
            33,
            10,
            21,
            27,
            31,
            37,
            34,
            20,
            29,
            43,
            11,
            35,
            49,
            14,
            39,
            9
        ],
        "topk_dict": {
            "top1": 0.9468
        },
        "trained": false
    },
    {
        "accuracy": 0.9484,
        "accuracy_before_training": 0.943,
        "block": 41,
        "epochs": 48,
        "i": 17,
        "num_blocks_active": 36,
        "num_blocks_removed": 18,
        "recalc_cache": true,
        "removed_blocks": [
            19,
            33,
            10,
            21,
            27,
            31,
            37,
            34,
            20,
            29,
            43,
            11,
            35,
            49,
            14,
            39,
            9,
            41
        ],
        "topk_dict": {
            "top1": 0.9484
        },
        "trained": {
            "accuracy": 0.9484,
            "accuracy_gain": 0.005400000000000071,
            "checkpoint": "/scratch/vsv1g12/distillation/every_two_step-e50/to-ResNet-56/temp-4/alpha-0.5/baseline_1/0/iter_17_removed_18.pth.tar",
            "duration": 1583.6303300857544,
            "epochs": 48,
            "event": "trained",
            "i": 17,
            "iteration": 17,
            "removed_blocks": [
                19,
                33,
                10,
                21,
                27,
                31,
                37,
                34,
                20,
                29,
                43,
                11,
                35,
                49,
                14,
                39,
                9,
                41
            ],
            "topk_dict": {
                "top1": 0.9484
            },
            "total_epochs": 50
        }
    },
    {
        "accuracy": 0.9466,
        "block": 32,
        "i": 18,
        "num_blocks_active": 35,
        "num_blocks_removed": 19,
        "recalc_cache": true,
        "removed_blocks": [
            19,
            33,
            10,
            21,
            27,
            31,
            37,
            34,
            20,
            29,
            43,
            11,
            35,
            49,
            14,
            39,
            9,
            41,
            32
        ],
        "topk_dict": {
            "top1": 0.9466
        },
        "trained": false
    },
    {
        "accuracy": 0.947,
        "accuracy_before_training": 0.9418,
        "block": 13,
        "epochs": 37,
        "i": 19,
        "num_blocks_active": 34,
        "num_blocks_removed": 20,
        "recalc_cache": true,
        "removed_blocks": [
            19,
            33,
            10,
            21,
            27,
            31,
            37,
            34,
            20,
            29,
            43,
            11,
            35,
            49,
            14,
            39,
            9,
            41,
            32,
            13
        ],
        "topk_dict": {
            "top1": 0.947
        },
        "trained": {
            "accuracy": 0.947,
            "accuracy_gain": 0.005199999999999982,
            "checkpoint": "/scratch/vsv1g12/distillation/every_two_step-e50/to-ResNet-56/temp-4/alpha-0.5/baseline_1/0/iter_19_removed_20.pth.tar",
            "duration": 1531.3294696807861,
            "epochs": 37,
            "event": "trained",
            "i": 19,
            "iteration": 19,
            "removed_blocks": [
                19,
                33,
                10,
                21,
                27,
                31,
                37,
                34,
                20,
                29,
                43,
                11,
                35,
                49,
                14,
                39,
                9,
                41,
                32,
                13
            ],
            "topk_dict": {
                "top1": 0.947
            },
            "total_epochs": 50
        }
    },
    {
        "accuracy": 0.9416,
        "block": 28,
        "i": 20,
        "num_blocks_active": 33,
        "num_blocks_removed": 21,
        "recalc_cache": true,
        "removed_blocks": [
            19,
            33,
            10,
            21,
            27,
            31,
            37,
            34,
            20,
            29,
            43,
            11,
            35,
            49,
            14,
            39,
            9,
            41,
            32,
            13,
            28
        ],
        "topk_dict": {
            "top1": 0.9416
        },
        "trained": false
    },
    {
        "accuracy": 0.9448,
        "accuracy_before_training": 0.9386,
        "block": 46,
        "epochs": 39,
        "i": 21,
        "num_blocks_active": 32,
        "num_blocks_removed": 22,
        "recalc_cache": true,
        "removed_blocks": [
            19,
            33,
            10,
            21,
            27,
            31,
            37,
            34,
            20,
            29,
            43,
            11,
            35,
            49,
            14,
            39,
            9,
            41,
            32,
            13,
            28,
            46
        ],
        "topk_dict": {
            "top1": 0.9448
        },
        "trained": {
            "accuracy": 0.9448,
            "accuracy_gain": 0.006199999999999983,
            "checkpoint": "/scratch/vsv1g12/distillation/every_two_step-e50/to-ResNet-56/temp-4/alpha-0.5/baseline_1/0/iter_21_removed_22.pth.tar",
            "duration": 1491.1519749164581,
            "epochs": 39,
            "event": "trained",
            "i": 21,
            "iteration": 21,
            "removed_blocks": [
                19,
                33,
                10,
                21,
                27,
                31,
                37,
                34,
                20,
                29,
                43,
                11,
                35,
                49,
                14,
                39,
                9,
                41,
                32,
                13,
                28,
                46
            ],
            "topk_dict": {
                "top1": 0.9448
            },
            "total_epochs": 50
        }
    },
    {
        "accuracy": 0.9408,
        "block": 23,
        "i": 22,
        "num_blocks_active": 31,
        "num_blocks_removed": 23,
        "recalc_cache": true,
        "removed_blocks": [
            19,
            33,
            10,
            21,
            27,
            31,
            37,
            34,
            20,
            29,
            43,
            11,
            35,
            49,
            14,
            39,
            9,
            41,
            32,
            13,
            28,
            46,
            23
        ],
        "topk_dict": {
            "top1": 0.9408
        },
        "trained": false
    },
    {
        "accuracy": 0.9452,
        "accuracy_before_training": 0.9354,
        "block": 26,
        "epochs": 23,
        "i": 23,
        "num_blocks_active": 30,
        "num_blocks_removed": 24,
        "recalc_cache": true,
        "removed_blocks": [
            19,
            33,
            10,
            21,
            27,
            31,
            37,
            34,
            20,
            29,
            43,
            11,
            35,
            49,
            14,
            39,
            9,
            41,
            32,
            13,
            28,
            46,
            23,
            26
        ],
        "topk_dict": {
            "top1": 0.9452
        },
        "trained": {
            "accuracy": 0.9452,
            "accuracy_gain": 0.009800000000000031,
            "checkpoint": "/scratch/vsv1g12/distillation/every_two_step-e50/to-ResNet-56/temp-4/alpha-0.5/baseline_1/0/iter_23_removed_24.pth.tar",
            "duration": 1443.3305423259735,
            "epochs": 23,
            "event": "trained",
            "i": 23,
            "iteration": 23,
            "removed_blocks": [
                19,
                33,
                10,
                21,
                27,
                31,
                37,
                34,
                20,
                29,
                43,
                11,
                35,
                49,
                14,
                39,
                9,
                41,
                32,
                13,
                28,
                46,
                23,
                26
            ],
            "topk_dict": {
                "top1": 0.9452
            },
            "total_epochs": 50
        }
    },
    {
        "accuracy": 0.9396,
        "block": 17,
        "i": 24,
        "num_blocks_active": 29,
        "num_blocks_removed": 25,
        "recalc_cache": true,
        "removed_blocks": [
            19,
            33,
            10,
            21,
            27,
            31,
            37,
            34,
            20,
            29,
            43,
            11,
            35,
            49,
            14,
            39,
            9,
            41,
            32,
            13,
            28,
            46,
            23,
            26,
            17
        ],
        "topk_dict": {
            "top1": 0.9396
        },
        "trained": false
    },
    {
        "accuracy": 0.9338,
        "block": 4,
        "i": 25,
        "num_blocks_active": 28,
        "num_blocks_removed": 26,
        "recalc_cache": true,
        "removed_blocks": [
            19,
            33,
            10,
            21,
            27,
            31,
            37,
            34,
            20,
            29,
            43,
            11,
            35,
            49,
            14,
            39,
            9,
            41,
            32,
            13,
            28,
            46,
            23,
            26,
            17,
            4
        ],
        "topk_dict": {
            "top1": 0.9338
        },
        "trained": false
    },
    {
        "accuracy": 0.9404,
        "accuracy_before_training": 0.9278,
        "baseline": [
            [
                "ResNet-56",
                27,
                0.948333,
                0.9368,
                0.001009,
                0.000557
            ]
        ],
        "block": 24,
        "epochs": 26,
        "i": 26,
        "num_blocks_active": 27,
        "num_blocks_removed": 27,
        "recalc_cache": true,
        "removed_blocks": [
            19,
            33,
            10,
            21,
            27,
            31,
            37,
            34,
            20,
            29,
            43,
            11,
            35,
            49,
            14,
            39,
            9,
            41,
            32,
            13,
            28,
            46,
            23,
            26,
            17,
            4,
            24
        ],
        "topk_dict": {
            "top1": 0.9404
        },
        "trained": {
            "accuracy": 0.9404,
            "accuracy_gain": 0.012600000000000056,
            "checkpoint": "/scratch/vsv1g12/distillation/every_two_step-e50/to-ResNet-56/temp-4/alpha-0.5/baseline_1/0/iter_26_removed_27.pth.tar",
            "duration": 1351.519847869873,
            "epochs": 26,
            "event": "trained",
            "i": 26,
            "iteration": 26,
            "removed_blocks": [
                19,
                33,
                10,
                21,
                27,
                31,
                37,
                34,
                20,
                29,
                43,
                11,
                35,
                49,
                14,
                39,
                9,
                41,
                32,
                13,
                28,
                46,
                23,
                26,
                17,
                4,
                24
            ],
            "topk_dict": {
                "top1": 0.9404
            },
            "total_epochs": 50
        }
    }
]