[
    {
        "accuracy": 0.946,
        "all_blocks_num": 54,
        "blocks_array": [
            18,
            18,
            18,
            0
        ],
        "i": -1,
        "num_blocks_active": 54,
        "num_blocks_removed": 0,
        "recalc_cache": false,
        "removed_blocks": [],
        "topk_dict": {
            "top1": 0.946
        },
        "trained": false
    },
    {
        "accuracy": 0.9454,
        "block": 26,
        "i": 0,
        "num_blocks_active": 53,
        "num_blocks_removed": 1,
        "recalc_cache": true,
        "removed_blocks": [
            26
        ],
        "topk_dict": {
            "top1": 0.9454
        },
        "trained": false
    },
    {
        "accuracy": 0.945,
        "block": 35,
        "i": 1,
        "num_blocks_active": 52,
        "num_blocks_removed": 2,
        "recalc_cache": true,
        "removed_blocks": [
            26,
            35
        ],
        "topk_dict": {
            "top1": 0.945
        },
        "trained": false
    },
    {
        "accuracy": 0.9438,
        "block": 19,
        "i": 2,
        "num_blocks_active": 51,
        "num_blocks_removed": 3,
        "recalc_cache": true,
        "removed_blocks": [
            26,
            35,
            19
        ],
        "topk_dict": {
            "top1": 0.9438
        },
        "trained": false
    },
    {
        "accuracy": 0.941,
        "block": 21,
        "i": 3,
        "num_blocks_active": 50,
        "num_blocks_removed": 4,
        "recalc_cache": true,
        "removed_blocks": [
            26,
            35,
            19,
            21
        ],
        "topk_dict": {
            "top1": 0.941
        },
        "trained": false
    },
    {
        "accuracy": 0.939,
        "block": 38,
        "i": 4,
        "num_blocks_active": 49,
        "num_blocks_removed": 5,
        "recalc_cache": true,
        "removed_blocks": [
            26,
            35,
            19,
            21,
            38
        ],
        "topk_dict": {
            "top1": 0.939
        },
        "trained": false
    },
    {
        "accuracy": 0.9446,
        "accuracy_before_training": 0.9382,
        "block": 40,
        "epochs": 25,
        "i": 5,
        "num_blocks_active": 48,
        "num_blocks_removed": 6,
        "recalc_cache": true,
        "removed_blocks": [
            26,
            35,
            19,
            21,
            38,
            40
        ],
        "topk_dict": {
            "top1": 0.9446
        },
        "trained": {
            "accuracy": 0.9446,
            "accuracy_gain": 0.006399999999999961,
            "checkpoint": "/scratch/vsv1g12/distillation/fourshot/to-ResNet-56/temp-4/alpha-0.5/baseline_2/0/iter_5_removed_6.pth.tar",
            "duration": 1872.243815422058,
            "epochs": 25,
            "event": "trained",
            "i": 5,
            "iteration": 5,
            "removed_blocks": [
                26,
                35,
                19,
                21,
                38,
                40
            ],
            "topk_dict": {
                "top1": 0.9446
            },
            "total_epochs": 50
        }
    },
    {
        "accuracy": 0.943,
        "block": 7,
        "i": 6,
        "num_blocks_active": 47,
        "num_blocks_removed": 7,
        "recalc_cache": true,
        "removed_blocks": [
            26,
            35,
            19,
            21,
            38,
            40,
            7
        ],
        "topk_dict": {
            "top1": 0.943
        },
        "trained": false
    },
    {
        "accuracy": 0.9416,
        "block": 6,
        "i": 7,
        "num_blocks_active": 46,
        "num_blocks_removed": 8,
        "recalc_cache": true,
        "removed_blocks": [
            26,
            35,
            19,
            21,
            38,
            40,
            7,
            6
        ],
        "topk_dict": {
            "top1": 0.9416
        },
        "trained": false
    },
    {
        "accuracy": 0.939,
        "block": 20,
        "i": 8,
        "num_blocks_active": 45,
        "num_blocks_removed": 9,
        "recalc_cache": true,
        "removed_blocks": [
            26,
            35,
            19,
            21,
            38,
            40,
            7,
            6,
            20
        ],
        "topk_dict": {
            "top1": 0.939
        },
        "trained": false
    },
    {
        "accuracy": 0.9374,
        "block": 34,
        "i": 9,
        "num_blocks_active": 44,
        "num_blocks_removed": 10,
        "recalc_cache": true,
        "removed_blocks": [
            26,
            35,
            19,
            21,
            38,
            40,
            7,
            6,
            20,
            34
        ],
        "topk_dict": {
            "top1": 0.9374
        },
        "trained": false
    },
    {
        "accuracy": 0.9348,
        "block": 41,
        "i": 10,
        "num_blocks_active": 43,
        "num_blocks_removed": 11,
        "recalc_cache": true,
        "removed_blocks": [
            26,
            35,
            19,
            21,
            38,
            40,
            7,
            6,
            20,
            34,
            41
        ],
        "topk_dict": {
            "top1": 0.9348
        },
        "trained": false
    },
    {
        "accuracy": 0.9422,
        "accuracy_before_training": 0.9324,
        "block": 27,
        "epochs": 43,
        "i": 11,
        "num_blocks_active": 42,
        "num_blocks_removed": 12,
        "recalc_cache": true,
        "removed_blocks": [
            26,
            35,
            19,
            21,
            38,
            40,
            7,
            6,
            20,
            34,
            41,
            27
        ],
        "topk_dict": {
            "top1": 0.9422
        },
        "trained": {
            "accuracy": 0.9422,
            "accuracy_gain": 0.009800000000000031,
            "checkpoint": "/scratch/vsv1g12/distillation/fourshot/to-ResNet-56/temp-4/alpha-0.5/baseline_2/0/iter_11_removed_12.pth.tar",
            "duration": 1733.6600275039673,
            "epochs": 43,
            "event": "trained",
            "i": 11,
            "iteration": 11,
            "removed_blocks": [
                26,
                35,
                19,
                21,
                38,
                40,
                7,
                6,
                20,
                34,
                41,
                27
            ],
            "topk_dict": {
                "top1": 0.9422
            },
            "total_epochs": 50
        }
    },
    {
        "accuracy": 0.9406,
        "block": 11,
        "i": 12,
        "num_blocks_active": 41,
        "num_blocks_removed": 13,
        "recalc_cache": true,
        "removed_blocks": [
            26,
            35,
            19,
            21,
            38,
            40,
            7,
            6,
            20,
            34,
            41,
            27,
            11
        ],
        "topk_dict": {
            "top1": 0.9406
        },
        "trained": false
    },
    {
        "accuracy": 0.9382,
        "block": 22,
        "i": 13,
        "num_blocks_active": 40,
        "num_blocks_removed": 14,
        "recalc_cache": true,
        "removed_blocks": [
            26,
            35,
            19,
            21,
            38,
            40,
            7,
            6,
            20,
            34,
            41,
            27,
            11,
            22
        ],
        "topk_dict": {
            "top1": 0.9382
        },
        "trained": false
    },
    {
        "accuracy": 0.935,
        "block": 16,
        "i": 14,
        "num_blocks_active": 39,
        "num_blocks_removed": 15,
        "recalc_cache": true,
        "removed_blocks": [
            26,
            35,
            19,
            21,
            38,
            40,
            7,
            6,
            20,
            34,
            41,
            27,
            11,
            22,
            16
        ],
        "topk_dict": {
            "top1": 0.935
        },
        "trained": false
    },
    {
        "accuracy": 0.932,
        "block": 24,
        "i": 15,
        "num_blocks_active": 38,
        "num_blocks_removed": 16,
        "recalc_cache": true,
        "removed_blocks": [
            26,
            35,
            19,
            21,
            38,
            40,
            7,
            6,
            20,
            34,
            41,
            27,
            11,
            22,
            16,
            24
        ],
        "topk_dict": {
            "top1": 0.932
        },
        "trained": false
    },
    {
        "accuracy": 0.9268,
        "block": 37,
        "i": 16,
        "num_blocks_active": 37,
        "num_blocks_removed": 17,
        "recalc_cache": true,
        "removed_blocks": [
            26,
            35,
            19,
            21,
            38,
            40,
            7,
            6,
            20,
            34,
            41,
            27,
            11,
            22,
            16,
            24,
            37
        ],
        "topk_dict": {
            "top1": 0.9268
        },
        "trained": false
    },
    {
        "accuracy": 0.9388,
        "accuracy_before_training": 0.9228,
        "block": 9,
        "epochs": 40,
        "i": 17,
        "num_blocks_active": 36,
        "num_blocks_removed": 18,
        "recalc_cache": true,
        "removed_blocks": [
            26,
            35,
            19,
            21,
            38,
            40,
            7,
            6,
            20,
            34,
            41,
            27,
            11,
            22,
            16,
            24,
            37,
            9
        ],
        "topk_dict": {
            "top1": 0.9388
        },
        "trained": {
            "accuracy": 0.9388,
            "accuracy_gain": 0.016000000000000014,
            "checkpoint": "/scratch/vsv1g12/distillation/fourshot/to-ResNet-56/temp-4/alpha-0.5/baseline_2/0/iter_17_removed_18.pth.tar",
            "duration": 1580.7482149600983,
            "epochs": 40,
            "event": "trained",
            "i": 17,
            "iteration": 17,
            "removed_blocks": [
                26,
                35,
                19,
                21,
                38,
                40,
                7,
                6,
                20,
                34,
                41,
                27,
                11,
                22,
                16,
                24,
                37,
                9
            ],
            "topk_dict": {
                "top1": 0.9388
            },
            "total_epochs": 50
        }
    },
    {
        "accuracy": 0.9352,
        "block": 32,
        "i": 18,
        "num_blocks_active": 35,
        "num_blocks_removed": 19,
        "recalc_cache": true,
        "removed_blocks": [
            26,
            35,
            19,
            21,
            38,
            40,
            7,
            6,
            20,
            34,
            41,
            27,
            11,
            22,
            16,
            24,
            37,
            9,
            32
        ],
        "topk_dict": {
            "top1": 0.9352
        },
        "trained": false
    },
    {
        "accuracy": 0.931,
        "block": 42,
        "i": 19,
        "num_blocks_active": 34,
        "num_blocks_removed": 20,
        "recalc_cache": true,
        "removed_blocks": [
            26,
            35,
            19,
            21,
            38,
            40,
            7,
            6,
            20,
            34,
            41,
            27,
            11,
            22,
            16,
            24,
            37,
            9,
            32,
            42
        ],
        "topk_dict": {
            "top1": 0.931
        },
        "trained": false
    },
    {
        "accuracy": 0.928,
        "block": 23,
        "i": 20,
        "num_blocks_active": 33,
        "num_blocks_removed": 21,
        "recalc_cache": true,
        "removed_blocks": [
            26,
            35,
            19,
            21,
            38,
            40,
            7,
            6,
            20,
            34,
            41,
            27,
            11,
            22,
            16,
            24,
            37,
            9,
            32,
            42,
            23
        ],
        "topk_dict": {
            "top1": 0.928
        },
        "trained": false
    },
    {
        "accuracy": 0.9236,
        "block": 17,
        "i": 21,
        "num_blocks_active": 32,
        "num_blocks_removed": 22,
        "recalc_cache": true,
        "removed_blocks": [
            26,
            35,
            19,
            21,
            38,
            40,
            7,
            6,
            20,
            34,
            41,
            27,
            11,
            22,
            16,
            24,
            37,
            9,
            32,
            42,
            23,
            17
        ],
        "topk_dict": {
            "top1": 0.9236
        },
        "trained": false
    },
    {
        "accuracy": 0.919,
        "block": 3,
        "i": 22,
        "num_blocks_active": 31,
        "num_blocks_removed": 23,
        "recalc_cache": true,
        "removed_blocks": [
            26,
            35,
            19,
            21,
            38,
            40,
            7,
            6,
            20,
            34,
            41,
            27,
            11,
            22,
            16,
            24,
            37,
            9,
            32,
            42,
            23,
            17,
            3
        ],
        "topk_dict": {
            "top1": 0.919
        },
        "trained": false
    },
    {
        "accuracy": 0.9116,
        "block": 50,
        "i": 23,
        "num_blocks_active": 30,
        "num_blocks_removed": 24,
        "recalc_cache": true,
        "removed_blocks": [
            26,
            35,
            19,
            21,
            38,
            40,
            7,
            6,
            20,
            34,
            41,
            27,
            11,
            22,
            16,
            24,
            37,
            9,
            32,
            42,
            23,
            17,
            3,
            50
        ],
        "topk_dict": {
            "top1": 0.9116
        },
        "trained": false
    },
    {
        "accuracy": 0.901,
        "block": 44,
        "i": 24,
        "num_blocks_active": 29,
        "num_blocks_removed": 25,
        "recalc_cache": true,
        "removed_blocks": [
            26,
            35,
            19,
            21,
            38,
            40,
            7,
            6,
            20,
            34,
            41,
            27,
            11,
            22,
            16,
            24,
            37,
            9,
            32,
            42,
            23,
            17,
            3,
            50,
            44
        ],
        "topk_dict": {
            "top1": 0.901
        },
        "trained": false
    },
    {
        "accuracy": 0.8912,
        "block": 14,
        "i": 25,
        "num_blocks_active": 28,
        "num_blocks_removed": 26,
        "recalc_cache": true,
        "removed_blocks": [
            26,
            35,
            19,
            21,
            38,
            40,
            7,
            6,
            20,
            34,
            41,
            27,
            11,
            22,
            16,
            24,
            37,
            9,
            32,
            42,
            23,
            17,
            3,
            50,
            44,
            14
        ],
        "topk_dict": {
            "top1": 0.8912
        },
        "trained": false
    },
    {
        "accuracy": 0.938,
        "accuracy_before_training": 0.8856,
        "baseline": [
            [
                "ResNet-56",
                27,
                0.948333,
                0.9368,
                0.001009,
                0.000557
            ]
        ],
        "block": 52,
        "epochs": 36,
        "i": 26,
        "num_blocks_active": 27,
        "num_blocks_removed": 27,
        "recalc_cache": true,
        "removed_blocks": [
            26,
            35,
            19,
            21,
            38,
            40,
            7,
            6,
            20,
            34,
            41,
            27,
            11,
            22,
            16,
            24,
            37,
            9,
            32,
            42,
            23,
            17,
            3,
            50,
            44,
            14,
            52
        ],
        "topk_dict": {
            "top1": 0.938
        },
        "trained": {
            "accuracy": 0.938,
            "accuracy_gain": 0.05239999999999989,
            "checkpoint": "/scratch/vsv1g12/distillation/fourshot/to-ResNet-56/temp-4/alpha-0.5/baseline_2/0/iter_26_removed_27.pth.tar",
            "duration": 1348.247915506363,
            "epochs": 36,
            "event": "trained",
            "i": 26,
            "iteration": 26,
            "removed_blocks": [
                26,
                35,
                19,
                21,
                38,
                40,
                7,
                6,
                20,
                34,
                41,
                27,
                11,
                22,
                16,
                24,
                37,
                9,
                32,
                42,
                23,
                17,
                3,
                50,
                44,
                14,
                52
            ],
            "topk_dict": {
                "top1": 0.938
            },
            "total_epochs": 50
        }
    }
]